growatt_public_api/__init__.py
growatt_public_api/growatt_api.py
growatt_public_api/growatt_types.py
growatt_public_api/api_v4/__init__.py
growatt_public_api/api_v4/api_v4.py
growatt_public_api/datalogger/__init__.py
growatt_public_api/datalogger/datalogger.py
growatt_public_api/device/__init__.py
growatt_public_api/device/device.py
growatt_public_api/env_sensor/__init__.py
growatt_public_api/env_sensor/env_sensor.py
growatt_public_api/groboost/__init__.py
growatt_public_api/groboost/groboost.py
growatt_public_api/hps/__init__.py
growatt_public_api/hps/hps.py
growatt_public_api/inverter/__init__.py
growatt_public_api/inverter/inverter.py
growatt_public_api/max/__init__.py
growatt_public_api/max/max.py
growatt_public_api/min/__init__.py
growatt_public_api/min/min.py
growatt_public_api/noah/__init__.py
growatt_public_api/noah/noah.py
growatt_public_api/pbd/__init__.py
growatt_public_api/pbd/pbd.py
growatt_public_api/pcs/__init__.py
growatt_public_api/pcs/pcs.py
growatt_public_api/plant/__init__.py
growatt_public_api/plant/plant.py
growatt_public_api/pydantic_models/__init__.py
growatt_public_api/pydantic_models/api_model.py
growatt_public_api/pydantic_models/api_v4.py
growatt_public_api/pydantic_models/device.py
growatt_public_api/pydantic_models/env_sensor.py
growatt_public_api/pydantic_models/groboost.py
growatt_public_api/pydantic_models/hps.py
growatt_public_api/pydantic_models/inverter.py
growatt_public_api/pydantic_models/max.py
growatt_public_api/pydantic_models/min.py
growatt_public_api/pydantic_models/noah.py
growatt_public_api/pydantic_models/pbd.py
growatt_public_api/pydantic_models/pcs.py
growatt_public_api/pydantic_models/plant.py
growatt_public_api/pydantic_models/smart_meter.py
growatt_public_api/pydantic_models/spa.py
growatt_public_api/pydantic_models/sph.py
growatt_public_api/pydantic_models/storage.py
growatt_public_api/pydantic_models/user.py
growatt_public_api/pydantic_models/vpp.py
growatt_public_api/session/__init__.py
growatt_public_api-2025.10.9.dist-info/METADATA
growatt_public_api-2025.10.9.dist-info/WHEEL
growatt_public_api-2025.10.9.dist-info/licenses/LICENSE
growatt_public_api-2025.10.9.dist-info/RECORD
