Metadata-Version: 2.4
Name: growatt_public_api
Version: 2025.10.9
Summary: Python implementation of Growatt public REST API
Project-URL: Homepage, https://github.com/timohencken/GrowattPublicApiPy
Project-URL: Issues, https://github.com/timohencken/GrowattPublicApiPy/issues
Author-email: Timo Hencken <github@hencken.de>
License-Expression: MIT
License-File: LICENSE
Classifier: Operating System :: OS Independent
Classifier: Programming Language :: Python :: 3
Requires-Python: >=3.10
Requires-Dist: loguru>0.7
Requires-Dist: pydantic<2.9,>=2.0
Requires-Dist: requests<3.0.0,>=2.27.1
